robotframework_libtoc/__init__.py
robotframework_libtoc/homepage_template.html
robotframework_libtoc/libtoc.py
robotframework_libtoc/toc_template.html
robotframework_libtoc-1.4.3.dist-info/LICENSE
robotframework_libtoc-1.4.3.dist-info/METADATA
robotframework_libtoc-1.4.3.dist-info/WHEEL
robotframework_libtoc-1.4.3.dist-info/entry_points.txt
robotframework_libtoc-1.4.3.dist-info/RECORD
