Metadata-Version: 2.1
Name: robotframework-libtoc
Version: 1.4.3
Summary: Docs and TOC generator for Robot Framework resources and libs
Home-page: https://github.com/amochin/robotframework-libtoc
License: Apache-2.0
Author: Andre Mochinin
Requires-Python: >=3.7
Classifier: License :: OSI Approved :: Apache Software License
Classifier: Programming Language :: Python :: 3
Classifier: Programming Language :: Python :: 3.7
Classifier: Programming Language :: Python :: 3.8
Classifier: Programming Language :: Python :: 3.9
Classifier: Programming Language :: Python :: 3.10
Classifier: Programming Language :: Python :: 3.11
Classifier: Programming Language :: Python :: 3.12
Requires-Dist: importlib-resources (>=5.12,<5.13)
Requires-Dist: robotframework (>=4)
